{
  "annotator_id": "67c72a3ce6327e6ac2aaabbc",
  "demographics": {
    "age": "78",
    "expertise": "home care",
    "practice_location": "burlington, vt",
    "race": "white",
    "sex": "female",
    "submitted_at": "2026-01-23T19:04:10.881629",
    "years_of_practice": "10"
  },
  "dataset": "usmle_sample",
  "model_key": "llama_sft",
  "case_id": "usmle_sample_246",
  "agent_name": "default_agent",
  "agent_model": "allenai/Llama-3.1-Tulu-3-8B-SFT",
  "correct_answer": "5",
  "correct_answer_idx": "C",
  "step1": {
    "answer": "C",
    "answer_belief": 0.1,
    "is_correct": true
  },
  "step2": {
    "answer": "A",
    "answer_belief": 0.14,
    "is_correct": false
  },
  "step3": {
    "answer": "A",
    "answer_belief": 0.14,
    "is_correct": false
  },
  "step1_to_step2_changes": {
    "answer_changed": true,
    "answer_belief_changed": true
  },
  "step2_to_step3_changes": {
    "answer_changed": false,
    "answer_belief_changed": false
  },
  "reasoning": "I changed my answer, and should have stayed with my original thought on these patients",
  "highlights": [],
  "session_start": "2026-01-23T19:04:10.906998",
  "step1_time": "2026-01-23T19:24:17.538751",
  "step2_time": "2026-01-23T19:26:14.532666",
  "step3_time": "2026-01-23T19:27:06.858319",
  "timestamp": "2026-01-23T19:27:06.858328"
}